{"id":"c554d218-9aae-4ce4-b774-dc831b72780e","revision":0,"last_node_id":6,"last_link_id":5,"nodes":[{"id":3,"type":"ComfyUI_HUD_IPAdapterFaceIDLoader","pos":[-140,-910],"size":[490,635],"flags":{},"order":2,"mode":0,"inputs":[{"localized_name":"image","name":"image","type":"IMAGE","link":1},{"localized_name":"model","name":"model","type":"MODEL","link":null},{"localized_name":"preset","name":"preset","type":"COMBO","widget":{"name":"preset"},"link":null},{"localized_name":"lora_strength","name":"lora_strength","type":"FLOAT","widget":{"name":"lora_strength"},"link":null},{"localized_name":"provider","name":"provider","type":"COMBO","widget":{"name":"provider"},"link":null},{"localized_name":"clip_vision_file","name":"clip_vision_file","type":"COMBO","widget":{"name":"clip_vision_file"},"link":null},{"localized_name":"insightface_provider","name":"insightface_provider","type":"COMBO","widget":{"name":"insightface_provider"},"link":null},{"localized_name":"insightface_model","name":"insightface_model","type":"COMBO","widget":{"name":"insightface_model"},"link":null},{"localized_name":"debug_mode","name":"debug_mode","shape":7,"type":"BOOLEAN","widget":{"name":"debug_mode"},"link":null}],"outputs":[{"localized_name":"model","name":"model","type":"MODEL","links":[2]},{"localized_name":"ipadapter","name":"ipadapter","type":"IPADAPTER","links":[3]},{"localized_name":"image","name":"image","type":"IMAGE","links":[4]},{"localized_name":"clip_vision","name":"clip_vision","type":"CLIP_VISION","links":[5]},{"localized_name":"insightface","name":"insightface","type":"INSIGHTFACE","links":null}],"properties":{"Node name for S&R":"ComfyUI_HUD_IPAdapterFaceIDLoader"},"widgets_values":["ip-adapter-faceid-plus_sd15.bin",0.6,"CUDA","Auto","CUDA","buffalo_l",false,""]},{"id":4,"type":"ComfyUI_HUD_BatchImagesMaskEditor","pos":[-475,-910],"size":[260,665],"flags":{},"order":0,"mode":0,"inputs":[],"outputs":[{"localized_name":"images","name":"images","type":"IMAGE","links":[1]},{"localized_name":"masks","name":"masks","type":"MASK","links":null}],"properties":{"hud_batch_mask_editor_slots":[{"image":"","mask":""},{"image":"","mask":""}],"hud_batch_mask_preview_mode":"overlay","Node name for S&R":"ComfyUI_HUD_BatchImagesMaskEditor"},"widgets_values":[""]},{"id":6,"type":"IPAdapterFaceID","pos":[450,-910],"size":[270,439.328125],"flags":{},"order":1,"mode":0,"inputs":[{"localized_name":"model","name":"model","type":"MODEL","link":2},{"localized_name":"ipadapter","name":"ipadapter","type":"IPADAPTER","link":3},{"localized_name":"image","name":"image","type":"IMAGE","link":4},{"localized_name":"image_negative","name":"image_negative","shape":7,"type":"IMAGE","link":null},{"localized_name":"attn_mask","name":"attn_mask","shape":7,"type":"MASK","link":null},{"localized_name":"clip_vision","name":"clip_vision","shape":7,"type":"CLIP_VISION","link":5},{"localized_name":"insightface","name":"insightface","shape":7,"type":"INSIGHTFACE","link":null},{"localized_name":"weight","name":"weight","type":"FLOAT","widget":{"name":"weight"},"link":null},{"localized_name":"weight_faceidv2","name":"weight_faceidv2","type":"FLOAT","widget":{"name":"weight_faceidv2"},"link":null},{"localized_name":"weight_type","name":"weight_type","type":"COMBO","widget":{"name":"weight_type"},"link":null},{"localized_name":"combine_embeds","name":"combine_embeds","type":"COMBO","widget":{"name":"combine_embeds"},"link":null},{"localized_name":"start_at","name":"start_at","type":"FLOAT","widget":{"name":"start_at"},"link":null},{"localized_name":"end_at","name":"end_at","type":"FLOAT","widget":{"name":"end_at"},"link":null},{"localized_name":"embeds_scaling","name":"embeds_scaling","type":"COMBO","widget":{"name":"embeds_scaling"},"link":null}],"outputs":[{"localized_name":"MODEL","name":"MODEL","type":"MODEL","links":null},{"localized_name":"face_image","name":"face_image","type":"IMAGE","links":null}],"properties":{"cnr_id":"comfyui_ipadapter_plus","ver":"a0f451a5113cf9becb0847b92884cb10cbdec0ef","Node name for S&R":"IPAdapterFaceID"},"widgets_values":[1,1,"linear","concat",0,1,"V only"]}],"links":[[1,4,0,3,0,"IMAGE"],[2,3,0,6,0,"MODEL"],[3,3,1,6,1,"IPADAPTER"],[4,3,2,6,2,"IMAGE"],[5,3,3,6,5,"CLIP_VISION"]],"groups":[],"config":{},"extra":{"ds":{"scale":0.6575793352652868,"offset":[968.8631519380725,1151.293489355794]}},"version":0.4}